pymeca/__init__.py
pymeca/contracts_abi/MecaDAO.json
pymeca/contracts_abi/MecaHost.json
pymeca/contracts_abi/MecaScheduler.json
pymeca/contracts_abi/MecaTask.json
pymeca/contracts_abi/MecaTower.json
pymeca/dao.py
pymeca/dao_contract_address.txt
pymeca/host.py
pymeca/pymeca.py
pymeca/scripts/abi.py
pymeca/scripts/deploy.py
pymeca/scripts/ganache.py
pymeca/task.py
pymeca/tower.py
pymeca/user.py
pymeca/utils.py
pymeca-0.1.2.dist-info/LICENSE
pymeca-0.1.2.dist-info/METADATA
pymeca-0.1.2.dist-info/WHEEL
pymeca-0.1.2.dist-info/RECORD
