Metadata-Version: 2.1
Name: pymeca
Version: 0.1.2
Summary: A middleware python package for interacting with the MECAnywhere smart contracts
License: MIT
Author: Stefan-Dan Ciocirlan (sdcioc)
Requires-Python: >=3.10,<4.0
Classifier: License :: OSI Approved :: MIT License
Classifier: Programming Language :: Python :: 3
Classifier: Programming Language :: Python :: 3.10
Classifier: Programming Language :: Python :: 3.11
Classifier: Programming Language :: Python :: 3.12
Requires-Dist: py-multiformats-cid (>=0.4.4)
Requires-Dist: py-solc-x (>=2.0.2)
Requires-Dist: web3[tester] (>=6.15.1)
